{
  "fndesk": {
    "display_name": "飞牛桌面管理工具",
    "desc": "多处自定样式主题美化,桌面图标任君摆布,让飞牛成为你的导航页，收藏夹,Docker应用入口~<br>• 🎵 飞牛桌面音乐播放器正式上线！从此桌面不再沉默<br> • ✨ 桌面图标、文件夹完全自由设置，彻底取代收藏夹<br>• 🌈 多项个性化设置：背景，LOGO，标题，预设主题等<br>• 🌐 内外网链接智能识别跳转，更可自定义更多链接<br>• 👑 多层文件夹，最小化托盘，右键菜单，拓展更多功能<br>• ⚙️ 更多自定义：外链分享页，登录页备案信息，飞牛影视<br><br>更多信息请关注:<br>• 飞牛论坛（搜：飞牛桌面管理工具）或 GitHub：IMGZCQ/fndesk",
    "labels": "工具,效率,美化",
    "version": "0.90.4",
    "download_url": "https://fndesk.imcq.top/FPK/fndesk.fpk", 
    "author": "米恋泥",
    "author_url": "https://github.com/IMGZCQ/FnDepot",
    "bug_report_url": "https://github.com/IMGZCQ/FnDepot/issues",
    "install_type": "系统空间",
    "size": "0.963",
    "history": {
      "v0.91":"🎵 Fndesk音乐播放器正式上线！从此桌面不再沉默~修复图标配置文件偶发乱码问题",
      "v0.90.4":"✅ 音乐播放器内测！适配飞牛1.1.7,增加左右键点击音效,修复密码文件暴露风险",
      "v0.90":"☑️ 增加一键添加Docker图标,效率暴升！修复文件夹右键菜单失效",
      "v0.89":"☑️ 系统图标支持塞进文件夹！鼠标放在标题设置项上有彩蛋！大幅提升程序启动速度！",
      "v0.88":"☑️ 支持自定义访问端口,HTTP和HTTPS共用一个端口,应用中心增加右键菜单Fndepot, 取消fndesk服务图标的显示",
      "v0.86":"☑️ 此版起支持在线升级！适配飞牛1.1.4",
      "v0.85":"📢 支持创建飞牛原生图标！APP也能用完美支持FN Connect，适配飞牛内测版1.1.2",
      "v0.83":"☑️ 适配飞牛1.1.0内测版,每个图标/文件夹独立开关,页內窗口/文件夹增加明暗色调ui风格,修复删除文件夹后所属图标无家可归",
      "v0.80":"✅ 外链分享自定义(PC和移动Web端Logo标题描述链接等),优化一键还原,还原后不需要重启,优化窗口最大化/调整默认排序"
    }
  }, 
    "fncube": {
    "display_name": "三阶魔方",
    "desc": "一个完整的三阶魔方",
    "labels": "娱乐, 益智",
    "version": "0.88",
    "download_url": "https://fndesk.imcq.top/FPK/fncube.fpk", 
    "author": "米恋泥",
    "author_url": "https://github.com/IMGZCQ/FnDepot",
    "bug_report_url": "https://github.com/IMGZCQ/FnDepot/issues",
    "install_type": "系统空间",
    "size": "0.455",
    "history": {"v0.88":"优化运行环境,支持所有网络下运行,不占用任何端口","v0.77":"修复错误,性能优化"}
  }, 
    "boombird": {
    "display_name": "压爆只雀",
    "desc": "压扁小鸟的解压小游戏",
    "labels": "娱乐, 解压",
    "version": "0.88",
    "download_url": "https://fndesk.imcq.top/FPK/boombird.fpk", 
    "author": "米恋泥",
    "author_url": "https://github.com/IMGZCQ/FnDepot",
    "bug_report_url": "https://github.com/IMGZCQ/FnDepot/issues",
    "install_type": "系统空间",
    "size": "0.895",
    "history": {"v0.88":"优化运行环境,支持所有网络下运行,不占用任何端口","v0.77":"修复错误,性能优化"}
  }, 
    "cutcubes": {
    "display_name": "切碎方块",
    "desc": "切碎方块的解压小游戏",
    "labels": "娱乐, 解压",
    "version": "0.88",
    "download_url": "https://fndesk.imcq.top/FPK/cutcubes.fpk", 
    "author": "米恋泥",
    "author_url": "https://github.com/IMGZCQ/FnDepot",
    "bug_report_url": "https://github.com/IMGZCQ/FnDepot/issues",
    "install_type": "系统空间",
    "size": "0.676",
    "history": {"v0.88":"手动汉化, 优化运行环境,支持所有网络下运行,不占用任何端口","v0.77":"修复错误,性能优化"}
  }
}
